xyplot/__init__.py
xyplot/curve.py
xyplot/curveFunc.py
xyplot-0.2.0.dist-info/LICENSE
xyplot-0.2.0.dist-info/METADATA
xyplot-0.2.0.dist-info/WHEEL
xyplot-0.2.0.dist-info/top_level.txt
xyplot-0.2.0.dist-info/RECORD
