Metadata-Version: 2.1
Name: xyplot
Version: 0.2.0
Summary: Plotting with python made easy
Home-page: https://github.com/xypnox/xyplot
Author: xypnox
Author-email: xypnox@gmail.com
License: UNKNOWN
Platform: UNKNOWN
Classifier: Programming Language :: Python :: 3
Classifier: License :: OSI Approved :: GNU General Public License v2 (GPLv2)
Classifier: Operating System :: OS Independent
Requires-Dist: matplotlib
Requires-Dist: numpy
